py_silhouette/__init__.py
py_silhouette/device.py
py_silhouette/version.py
py_silhouette-0.6.1.dist-info/METADATA
py_silhouette-0.6.1.dist-info/WHEEL
py_silhouette-0.6.1.dist-info/top_level.txt
py_silhouette-0.6.1.dist-info/RECORD
