Metadata-Version: 2.4
Name: py_silhouette
Version: 0.6.1
Summary: A USB driver and Python API to control the Silhouette Portrait plotter.
Home-page: https://github.com/mossblaser/py_silhouette
Author: Jonathan Heathcote
License: LGPLv3
Keywords: plotter cutter driver usb silhouette
Classifier: Development Status :: 3 - Alpha
Classifier: Intended Audience :: Developers
Classifier: License :: OSI Approved :: GNU Lesser General Public License v3 (LGPLv3)
Classifier: Operating System :: POSIX :: Linux
Classifier: Operating System :: Microsoft :: Windows
Classifier: Operating System :: MacOS
Classifier: Programming Language :: Python :: 2
Classifier: Programming Language :: Python :: 2.7
Classifier: Programming Language :: Python :: 3
Classifier: Programming Language :: Python :: 3.5
Requires-Dist: pyusb>=1.0.0
Requires-Dist: attrs>=18.0.0
Dynamic: author
Dynamic: classifier
Dynamic: home-page
Dynamic: keywords
Dynamic: license
Dynamic: requires-dist
Dynamic: summary
